quickfix40.py
quickfix50.py
quickfix44.py
quickfix41.py
quickfix.py
quickfix50sp1.py
_quickfix.cpython-312-darwin.so
quickfix50sp2.py
quickfix42.py
quickfixt11.py
quickfix43.py
quickfix_py-0.0.3.dist-info/RECORD
quickfix_py-0.0.3.dist-info/WHEEL
quickfix_py-0.0.3.dist-info/top_level.txt
quickfix_py-0.0.3.dist-info/METADATA
quickfix_py-0.0.3.dist-info/licenses/LICENSE
quickfix_py-0.0.3.data/data/share/quickfix/FIX50SP1.xml
quickfix_py-0.0.3.data/data/share/quickfix/FIX50SP2.xml
quickfix_py-0.0.3.data/data/share/quickfix/FIXT11.xml
quickfix_py-0.0.3.data/data/share/quickfix/FIX50.xml
quickfix_py-0.0.3.data/data/share/quickfix/FIX44.xml
quickfix_py-0.0.3.data/data/share/quickfix/FIX40.xml
quickfix_py-0.0.3.data/data/share/quickfix/FIX41.xml
quickfix_py-0.0.3.data/data/share/quickfix/FIX43.xml
quickfix_py-0.0.3.data/data/share/quickfix/FIX42.xml
quickfix_py.dylibs/libssl.3.dylib
quickfix_py.dylibs/libcrypto.3.dylib
