Metadata-Version: 2.4
Name: quickfix-py
Version: 0.0.3
Summary: Python package for Quickfix C++, FIX (Financial Information eXchange) protocol implementation
Home-page: https://github.com/pablodcar/quickfix-py-package
Download-URL: https://github.com/pablodcar/quickfix-py-package
Author-email: pablodcar@gmail.com
Maintainer: Pablo Carballo
Maintainer-email: pablodcar@gmail.com
License: The QuickFIX Software License, Version 1.0
Requires-Python: >=3.11
License-File: LICENSE
Dynamic: author-email
Dynamic: description
Dynamic: description-content-type
Dynamic: download-url
Dynamic: home-page
Dynamic: license
Dynamic: license-file
Dynamic: maintainer
Dynamic: maintainer-email
Dynamic: requires-python
Dynamic: summary
